ast_canopy/__init__.py
ast_canopy/api.py
ast_canopy/decl.py
ast_canopy/fdcap_min.py
ast_canopy/instantiations.py
ast_canopy/pylibastcanopy.cpp
ast_canopy/pylibastcanopy.cpython-313-x86_64-linux-gnu.so
ast_canopy/pylibastcanopy.pyi
ast_canopy/shim_include/texture_fetch_functions.h
ast_canopy.libs/libastcanopy-ed1d050a.so
ast_canopy-0.6.0.dist-info/LICENSE
ast_canopy-0.6.0.dist-info/METADATA
ast_canopy-0.6.0.dist-info/WHEEL
ast_canopy-0.6.0.dist-info/RECORD
