Metadata-Version: 2.2
Name: ast_canopy
Version: 0.6.0
